scb/__init__.py
scb/scb.py
scb-0.1.2.dist-info/LICENSE
scb-0.1.2.dist-info/METADATA
scb-0.1.2.dist-info/WHEEL
scb-0.1.2.dist-info/top_level.txt
scb-0.1.2.dist-info/RECORD
